{
    "Txt_Name": "Card_3130004_2",
    "Dialogue": [
        {
            "index": 1,
            "heroineId": [
                13
            ],
            "name": "丸山利恵",
            "message": "今日は悪かったわね。\n無駄足になっちゃって。",
            "voice": "card/card_13/Card_3130004_2/card_3130004_2_001.mp3"
        },
        {
            "index": 2,
            "heroineId": [
                16
            ],
            "name": "遠見鳴",
            "message": "どうせだから、ちょっと散歩していかない？\nイルミネーションを観に行こうよ。",
            "voice": "card/card_13/Card_3130004_2/card_3130004_2_002.mp3"
        },
        {
            "index": 3,
            "heroineId": [
                13
            ],
            "name": "丸山利恵",
            "message": "イルミネーション？",
            "voice": "card/card_13/Card_3130004_2/card_3130004_2_003.mp3"
        },
        {
            "index": 4,
            "heroineId": [
                16
            ],
            "name": "遠見鳴",
            "message": "隣の駅前広場のイルミネーションが、\nとてもキレイらしいの。",
            "voice": "card/card_13/Card_3130004_2/card_3130004_2_004.mp3"
        },
        {
            "index": 5,
            "heroineId": [
                13
            ],
            "name": "丸山利恵",
            "message": "わかったわ。\nじゃあさっそく電車に……。",
            "voice": "card/card_13/Card_3130004_2/card_3130004_2_005.mp3"
        },
        {
            "index": 6,
            "heroineId": [
                16
            ],
            "name": "遠見鳴",
            "message": "すぐそこだから歩こ。",
            "voice": "card/card_13/Card_3130004_2/card_3130004_2_006.mp3"
        },
        {
            "index": 7,
            "heroineId": [
                13
            ],
            "name": "丸山利恵",
            "message": "そう遠くないし、それでもいいか。",
            "voice": "card/card_13/Card_3130004_2/card_3130004_2_007.mp3"
        },
        {
            "index": 8,
            "heroineId": [
                16
            ],
            "name": "遠見鳴",
            "message": "うん。\n行こう。",
            "voice": "card/card_13/Card_3130004_2/card_3130004_2_008.mp3"
        },
        {
            "index": 9,
            "heroineId": [
                16
            ],
            "name": "遠見鳴",
            "message": "平日なのに、すごい人だね。",
            "voice": "card/card_13/Card_3130004_2/card_3130004_2_009.mp3"
        },
        {
            "index": 10,
            "heroineId": [
                13
            ],
            "name": "丸山利恵",
            "message": "……っん？\n何か言った？",
            "voice": "card/card_13/Card_3130004_2/card_3130004_2_010.mp3"
        },
        {
            "index": 11,
            "heroineId": [
                16
            ],
            "name": "遠見鳴",
            "message": "夢中になって、何を見てたの？",
            "voice": "card/card_13/Card_3130004_2/card_3130004_2_011.mp3"
        },
        {
            "index": 12,
            "heroineId": [
                13
            ],
            "name": "丸山利恵",
            "message": "あれ何だろ……。\nほら、あそこに長い行列ができてる。",
            "voice": "card/card_13/Card_3130004_2/card_3130004_2_012.mp3"
        },
        {
            "index": 13,
            "heroineId": [
                16
            ],
            "name": "遠見鳴",
            "message": "ああ。タピオカの店ね。\n今、大人気なの。食べたことない？ ",
            "voice": "card/card_13/Card_3130004_2/card_3130004_2_013.mp3"
        },
        {
            "index": 14,
            "heroineId": [
                13
            ],
            "name": "丸山利恵",
            "message": "ああいう流行りものには興味がないの。\nあの列に並ばなきゃいけないんでしょ？ ",
            "voice": "card/card_13/Card_3130004_2/card_3130004_2_014.mp3"
        },
        {
            "index": 15,
            "heroineId": [
                16
            ],
            "name": "遠見鳴",
            "message": "利恵は、並ぶの嫌いだもんね。",
            "voice": "card/card_13/Card_3130004_2/card_3130004_2_015.mp3"
        },
        {
            "index": 16,
            "heroineId": [
                13
            ],
            "name": "丸山利恵",
            "message": "前に一度だけ、\n夢の国と呼ばれる遊園地に行ったことがあるの。",
            "voice": "card/card_13/Card_3130004_2/card_3130004_2_016.mp3"
        },
        {
            "index": 17,
            "heroineId": [
                16
            ],
            "name": "遠見鳴",
            "message": "利恵が？\n珍しい。",
            "voice": "card/card_13/Card_3130004_2/card_3130004_2_017.mp3"
        },
        {
            "index": 18,
            "heroineId": [
                13
            ],
            "name": "丸山利恵",
            "message": "でも、並ぶのは嫌で、1つも乗り物に乗らなかったわ。",
            "voice": "card/card_13/Card_3130004_2/card_3130004_2_018.mp3"
        },
        {
            "index": 19,
            "heroineId": [
                16
            ],
            "name": "遠見鳴",
            "message": "そんなに嫌なの……。",
            "voice": "card/card_13/Card_3130004_2/card_3130004_2_019.mp3"
        },
        {
            "index": 20,
            "heroineId": [
                13
            ],
            "name": "丸山利恵",
            "message": "でも、試しに並んでみようかな……。",
            "voice": "card/card_13/Card_3130004_2/card_3130004_2_020.mp3"
        },
        {
            "index": 21,
            "heroineId": [
                16
            ],
            "name": "遠見鳴",
            "message": "うん。\nそうしよ。",
            "voice": "card/card_13/Card_3130004_2/card_3130004_2_021.mp3"
        },
        {
            "index": 22,
            "heroineId": [
                13
            ],
            "name": "丸山利恵",
            "message": "これがタピオカミルクティー……。\nこの、カラスの目玉のようなものが、タピオカなの？",
            "voice": "card/card_13/Card_3130004_2/card_3130004_2_022.mp3"
        },
        {
            "index": 23,
            "heroineId": [
                16
            ],
            "name": "遠見鳴",
            "message": "美味しそうでしょう？\n飲んでみて。",
            "voice": "card/card_13/Card_3130004_2/card_3130004_2_023.mp3"
        },
        {
            "index": 24,
            "heroineId": [
                13
            ],
            "name": "丸山利恵",
            "message": "くにゅくにゅした不思議な食感ね……。",
            "voice": "card/card_13/Card_3130004_2/card_3130004_2_024.mp3"
        },
        {
            "index": 25,
            "heroineId": [
                16
            ],
            "name": "遠見鳴",
            "message": "どう？\nイマイチ？",
            "voice": "card/card_13/Card_3130004_2/card_3130004_2_025.mp3"
        },
        {
            "index": 26,
            "heroineId": [
                13
            ],
            "name": "丸山利恵",
            "message": "美味！　非常に美味である！\nこんなに美味であったとは知らなかった……。",
            "voice": "card/card_13/Card_3130004_2/card_3130004_2_026.mp3"
        },
        {
            "index": 27,
            "heroineId": [
                16
            ],
            "name": "遠見鳴",
            "message": "たまには、並んでみるのもいいものでしょ。",
            "voice": "card/card_13/Card_3130004_2/card_3130004_2_027.mp3"
        },
        {
            "index": 28,
            "heroineId": [
                13
            ],
            "name": "丸山利恵",
            "message": "うん。\n確かにそうね。",
            "voice": "card/card_13/Card_3130004_2/card_3130004_2_028.mp3"
        },
        {
            "index": 29,
            "heroineId": [
                16
            ],
            "name": "遠見鳴",
            "message": "あ、イルミネーションはそこの広場だよ。",
            "voice": "card/card_13/Card_3130004_2/card_3130004_2_029.mp3"
        },
        {
            "index": 30,
            "heroineId": [
                16
            ],
            "name": "遠見鳴",
            "message": "あれ……？",
            "voice": "card/card_13/Card_3130004_2/card_3130004_2_030.mp3"
        },
        {
            "index": 31,
            "heroineId": [
                13
            ],
            "name": "丸山利恵",
            "message": "真っ暗ね……。",
            "voice": "card/card_13/Card_3130004_2/card_3130004_2_031.mp3"
        },
        {
            "index": 32,
            "heroineId": [
                16
            ],
            "name": "遠見鳴",
            "message": "おかしいな。\nネットで調べてみるね……、あっ！",
            "voice": "card/card_13/Card_3130004_2/card_3130004_2_032.mp3"
        },
        {
            "index": 33,
            "heroineId": [
                13
            ],
            "name": "丸山利恵",
            "message": "どうかした？",
            "voice": "card/card_13/Card_3130004_2/card_3130004_2_033.mp3"
        },
        {
            "index": 34,
            "heroineId": [
                16
            ],
            "name": "遠見鳴",
            "message": "先週で終わってた……、ごめん。",
            "voice": "card/card_13/Card_3130004_2/card_3130004_2_034.mp3"
        },
        {
            "index": 35,
            "heroineId": [
                13
            ],
            "name": "丸山利恵",
            "message": "ふふふ……。",
            "voice": "card/card_13/Card_3130004_2/card_3130004_2_035.mp3"
        },
        {
            "index": 36,
            "heroineId": [
                16
            ],
            "name": "遠見鳴",
            "message": "利恵？\nなにがおかしいの？",
            "voice": "card/card_13/Card_3130004_2/card_3130004_2_036.mp3"
        },
        {
            "index": 37,
            "heroineId": [
                13
            ],
            "name": "丸山利恵",
            "message": "いやいや……、そうか。これも先週で終わってたのか。\nお互い、しっかり調べておかないとダメね。",
            "voice": "card/card_13/Card_3130004_2/card_3130004_2_037.mp3"
        },
        {
            "index": 38,
            "heroineId": [
                16
            ],
            "name": "遠見鳴",
            "message": "何の話？",
            "voice": "card/card_13/Card_3130004_2/card_3130004_2_038.mp3"
        },
        {
            "index": 39,
            "heroineId": [
                13
            ],
            "name": "丸山利恵",
            "message": "結果から言えば、大満足だっていう話。\nとても楽しかった。",
            "voice": "card/card_13/Card_3130004_2/card_3130004_2_039.mp3"
        },
        {
            "index": 40,
            "heroineId": [
                13
            ],
            "name": "丸山利恵",
            "message": "さぁ、もう少し歩こう。\n鳴、付き合ってくれる？",
            "voice": "card/card_13/Card_3130004_2/card_3130004_2_040.mp3"
        }
    ]
}