{
    "Txt_Name": "Lesson_20108",
    "Dialogue": [
        {
            "index": 1,
            "heroineId": [
                7
            ],
            "name": "恵庭あいり",
            "message": "お父さんはいいから、急いでね。",
            "voice": "lesson/Lesson_20108/lesson_20108_001.mp3"
        },
        {
            "index": 2,
            "heroineId": [
                5
            ],
            "name": "天童悠希",
            "message": "え？　でもまだ左に100回混ぜてない……。",
            "voice": "lesson/Lesson_20108/lesson_20108_002.mp3"
        },
        {
            "index": 3,
            "heroineId": [
                7
            ],
            "name": "恵庭あいり",
            "message": "ホントに時間ないんだよ？",
            "voice": "lesson/Lesson_20108/lesson_20108_003.mp3"
        },
        {
            "index": 4,
            "heroineId": [
                1
            ],
            "name": "六石陽菜",
            "message": "なに？　どうしたの？",
            "voice": "lesson/Lesson_20108/lesson_20108_004.mp3"
        },
        {
            "index": 5,
            "heroineId": [
                7
            ],
            "name": "恵庭あいり",
            "message": "あ、陽菜さん……。",
            "voice": "lesson/Lesson_20108/lesson_20108_005.mp3"
        },
        {
            "index": 6,
            "heroineId": [
                1
            ],
            "name": "六石陽菜",
            "message": "あれ？　悠希ちゃん、学校行かなくて良いの？　\nテストでしょ？",
            "voice": "lesson/Lesson_20108/lesson_20108_006.mp3"
        },
        {
            "index": 7,
            "heroineId": [
                7
            ],
            "name": "恵庭あいり",
            "message": "陽菜さんからも悠希ちゃんに言って下さい。\nあいりがいくら言っても、悠希ちゃん全然急がなくって……。",
            "voice": "lesson/Lesson_20108/lesson_20108_007.mp3"
        },
        {
            "index": 8,
            "heroineId": [
                5
            ],
            "name": "天童悠希",
            "message": "でも朝飯をキチンと食べないと、力が湧いてこないからなぁ。",
            "voice": "lesson/Lesson_20108/lesson_20108_000.mp3"
        },
        {
            "index": 9,
            "heroineId": [
                5
            ],
            "name": "天童悠希",
            "message": "戦の前の腹ごしらえ。食べねばテストに勝てんのよ。",
            "voice": "lesson/Lesson_20108/lesson_20108_000.mp3"
        },
        {
            "index": 10,
            "heroineId": [
                1
            ],
            "name": "六石陽菜",
            "message": "ご飯のためなら、遅刻も恐れないわけね？",
            "voice": "lesson/Lesson_20108/lesson_20108_009.mp3"
        },
        {
            "index": 11,
            "heroineId": [
                5
            ],
            "name": "天童悠希",
            "message": "察しが良いね、さすがリーダー！",
            "voice": "lesson/Lesson_20108/lesson_20108_010.mp3"
        },
        {
            "index": 12,
            "heroineId": [
                7
            ],
            "name": "恵庭あいり",
            "message": "感心してる場合じゃないでしょ！",
            "voice": "lesson/Lesson_20108/lesson_20108_011.mp3"
        },
        {
            "index": 13,
            "heroineId": [
                1
            ],
            "name": "六石陽菜",
            "message": "わかった。",
            "voice": "lesson/Lesson_20108/lesson_20108_012.mp3"
        },
        {
            "index": 14,
            "heroineId": [
                7
            ],
            "name": "恵庭あいり",
            "message": "陽菜さん……？",
            "voice": "lesson/Lesson_20108/lesson_20108_013.mp3"
        },
        {
            "index": 15,
            "heroineId": [
                1
            ],
            "name": "六石陽菜",
            "message": "後は、もう納豆でご飯食べるだけなんだよね？",
            "voice": "lesson/Lesson_20108/lesson_20108_014.mp3"
        },
        {
            "index": 16,
            "heroineId": [
                7
            ],
            "name": "恵庭あいり",
            "message": "そう……、みたいです。",
            "voice": "lesson/Lesson_20108/lesson_20108_015.mp3"
        },
        {
            "index": 17,
            "heroineId": [
                5
            ],
            "name": "天童悠希",
            "message": "そうだよ。",
            "voice": "lesson/Lesson_20108/lesson_20108_016.mp3"
        },
        {
            "index": 18,
            "heroineId": [
                1
            ],
            "name": "六石陽菜",
            "message": "じゃあ、わたしとあいりちゃんで悠希ちゃんの部屋から、\n制服とかカバンとか持って来てあげよう。",
            "voice": "lesson/Lesson_20108/lesson_20108_017.mp3"
        },
        {
            "index": 19,
            "heroineId": [
                5
            ],
            "name": "天童悠希",
            "message": "え？　いいの？",
            "voice": "lesson/Lesson_20108/lesson_20108_018.mp3"
        },
        {
            "index": 20,
            "heroineId": [
                1
            ],
            "name": "六石陽菜",
            "message": "食べ終わったらすぐに出発出来るようにしてあげよう。",
            "voice": "lesson/Lesson_20108/lesson_20108_019.mp3"
        },
        {
            "index": 21,
            "heroineId": [
                7
            ],
            "name": "恵庭あいり",
            "message": "なるほど。\nそうですね。そうしましょう！",
            "voice": "lesson/Lesson_20108/lesson_20108_020.mp3"
        },
        {
            "index": 22,
            "heroineId": [
                5
            ],
            "name": "天童悠希",
            "message": "あいり……、陽菜……。あたしのためにここまでしてくれるなんて。\nこのお礼はいつか必ず！",
            "voice": "lesson/Lesson_20108/lesson_20108_021.mp3"
        },
        {
            "index": 23,
            "heroineId": [
                7
            ],
            "name": "恵庭あいり",
            "message": "もう良いから早く食べちゃって！！",
            "voice": "lesson/Lesson_20108/lesson_20108_022.mp3"
        }
    ]
}