{
    "Txt_Name": "Lesson_31610",
    "Dialogue": [
        {
            "index": 1,
            "heroineId": [
                8
            ],
            "name": "九条柚葉",
            "message": "ふあ～あ……。",
            "voice": "lesson/Lesson_31610/lesson_31610_001.mp3"
        },
        {
            "index": 2,
            "heroineId": [
                8
            ],
            "name": "九条柚葉",
            "message": "ううん……、ん……。",
            "voice": "lesson/Lesson_31610/lesson_31610_002.mp3"
        },
        {
            "index": 3,
            "heroineId": [
                8
            ],
            "name": "九条柚葉",
            "message": "あら、今日も来てくれてるの？",
            "voice": "lesson/Lesson_31610/lesson_31610_003.mp3"
        },
        {
            "index": 4,
            "heroineId": [
                8
            ],
            "name": "九条柚葉",
            "message": "ふふっ。\nグッモーニン。",
            "voice": "lesson/Lesson_31610/lesson_31610_004.mp3"
        },
        {
            "index": 5,
            "heroineId": [
                6
            ],
            "name": "赤川千紗",
            "message": "悠希ー！　柚葉ー！\n朝よー。起きなさーい！",
            "voice": "lesson/Lesson_31610/lesson_31610_005.mp3"
        },
        {
            "index": 6,
            "heroineId": [
                8
            ],
            "name": "九条柚葉",
            "message": "はーい。チサ！\nもう起きてるわ！",
            "voice": "lesson/Lesson_31610/lesson_31610_006.mp3"
        },
        {
            "index": 7,
            "heroineId": [
                8
            ],
            "name": "九条柚葉",
            "message": "あなたが毎日来てくれたら、\nアラームなんて必要なくなるのにね。",
            "voice": "lesson/Lesson_31610/lesson_31610_007.mp3"
        },
        {
            "index": 8,
            "heroineId": [
                8
            ],
            "name": "九条柚葉",
            "message": "ほら、ね。\nアラームより早く起きれるもの。",
            "voice": "lesson/Lesson_31610/lesson_31610_008.mp3"
        }
    ]
}