{
    "Txt_Name": "Card_3100004_2",
    "Dialogue": [
        {
            "index": 1,
            "heroineId": [
                10
            ],
            "name": {
                "default": "神室絢"
            },
            "message": {
                "default": "運命よ、勝負だ！ "
            },
            "voice": "card/Card_10/Card_3100004_2/card_3100004_2_001.mp3"
        },
        {
            "index": 2,
            "heroineId": [
                9
            ],
            "name": {
                "default": "夜峰美晴"
            },
            "message": {
                "default": "……どうしたんだろ？　絢。"
            },
            "voice": "card/Card_10/Card_3100004_2/card_3100004_2_002.mp3"
        },
        {
            "index": 3,
            "heroineId": [
                11
            ],
            "name": {
                "default": "宮路まほろ"
            },
            "message": {
                "default": "ずっと、運命と勝負したがってる。"
            },
            "voice": "card/Card_10/Card_3100004_2/card_3100004_2_003.mp3"
        },
        {
            "index": 4,
            "heroineId": [
                12
            ],
            "name": {
                "default": "日名倉莉子"
            },
            "message": {
                "default": "最近ずっと機嫌よかったんだけどね。"
            },
            "voice": "card/Card_10/Card_3100004_2/card_3100004_2_004.mp3"
        },
        {
            "index": 5,
            "heroineId": [
                9
            ],
            "name": {
                "default": "夜峰美晴"
            },
            "message": {
                "default": "お年頃なのかも。"
            },
            "voice": "card/Card_10/Card_3100004_2/card_3100004_2_005.mp3"
        },
        {
            "index": 6,
            "heroineId": [
                12
            ],
            "name": {
                "default": "日名倉莉子"
            },
            "message": {
                "default": "わぁ、絢来たよ。"
            },
            "voice": "card/Card_10/Card_3100004_2/card_3100004_2_006.mp3"
        },
        {
            "index": 7,
            "heroineId": [
                10
            ],
            "name": {
                "default": "神室絢"
            },
            "message": {
                "default": "ねえ、美晴。"
            },
            "voice": "card/Card_10/Card_3100004_2/card_3100004_2_007.mp3"
        },
        {
            "index": 8,
            "heroineId": [
                10
            ],
            "name": {
                "default": "神室絢"
            },
            "message": {
                "default": "ペットショップの動物って、\nもし売れなかったらどうなるの？"
            },
            "voice": "card/Card_10/Card_3100004_2/card_3100004_2_008.mp3"
        },
        {
            "index": 9,
            "heroineId": [
                9
            ],
            "name": {
                "default": "夜峰美晴"
            },
            "message": {
                "default": "分からないなぁ。\n莉子は知ってる？"
            },
            "voice": "card/Card_10/Card_3100004_2/card_3100004_2_009.mp3"
        },
        {
            "index": 10,
            "heroineId": [
                12
            ],
            "name": {
                "default": "日名倉莉子"
            },
            "message": {
                "default": "いや、あたしだって知らないよ。"
            },
            "voice": "card/Card_10/Card_3100004_2/card_3100004_2_010.mp3"
        },
        {
            "index": 11,
            "heroineId": [
                11
            ],
            "name": {
                "default": "宮路まほろ"
            },
            "message": {
                "default": "ネットで調べたら？"
            },
            "voice": "card/Card_10/Card_3100004_2/card_3100004_2_011.mp3"
        },
        {
            "index": 12,
            "heroineId": [
                10
            ],
            "name": {
                "default": "神室絢"
            },
            "message": {
                "default": "調べたの。\nでもあいまいで。"
            },
            "voice": "card/Card_10/Card_3100004_2/card_3100004_2_012.mp3"
        },
        {
            "index": 13,
            "heroineId": [
                9
            ],
            "name": {
                "default": "夜峰美晴"
            },
            "message": {
                "default": "なんて書かれてたの？"
            },
            "voice": "card/Card_10/Card_3100004_2/card_3100004_2_013.mp3"
        },
        {
            "index": 14,
            "heroineId": [
                10
            ],
            "name": {
                "default": "神室絢"
            },
            "message": {
                "default": "処分する機関があって……。\nそこにお金を払って渡してるみたいなんだけど。"
            },
            "voice": "card/Card_10/Card_3100004_2/card_3100004_2_014.mp3"
        },
        {
            "index": 15,
            "heroineId": [
                9
            ],
            "name": {
                "default": "夜峰美晴"
            },
            "message": {
                "default": "どうしてそんなこと聞くの？"
            },
            "voice": "card/Card_10/Card_3100004_2/card_3100004_2_015.mp3"
        },
        {
            "index": 16,
            "heroineId": [
                10
            ],
            "name": {
                "default": "神室絢"
            },
            "message": {
                "default": "……。"
            },
            "voice": "card/Card_10/Card_3100004_2/card_3100004_2_016.mp3"
        },
        {
            "index": 17,
            "heroineId": [
                12
            ],
            "name": {
                "default": "日名倉莉子"
            },
            "message": {
                "default": "どうした？"
            },
            "voice": "card/Card_10/Card_3100004_2/card_3100004_2_017.mp3"
        },
        {
            "index": 18,
            "heroineId": [
                10
            ],
            "name": {
                "default": "神室絢"
            },
            "message": {
                "default": "笑わないで聞いてくれる？"
            },
            "voice": "card/Card_10/Card_3100004_2/card_3100004_2_018.mp3"
        },
        {
            "index": 19,
            "heroineId": [
                9
            ],
            "name": {
                "default": "夜峰美晴"
            },
            "message": {
                "default": "笑わないよ。"
            },
            "voice": "card/Card_10/Card_3100004_2/card_3100004_2_019.mp3"
        },
        {
            "index": 20,
            "heroineId": [
                10
            ],
            "name": {
                "default": "神室絢"
            },
            "message": {
                "default": "ペットショップの犬が欲しいの。"
            },
            "voice": "card/Card_10/Card_3100004_2/card_3100004_2_020.mp3"
        },
        {
            "index": 21,
            "heroineId": [
                12
            ],
            "name": {
                "default": "日名倉莉子"
            },
            "message": {
                "default": "……全然笑える要素なかったよ。"
            },
            "voice": "card/Card_10/Card_3100004_2/card_3100004_2_021.mp3"
        },
        {
            "index": 22,
            "heroineId": [
                10
            ],
            "name": {
                "default": "神室絢"
            },
            "message": {
                "default": "もう、虜なの。\nあの子のことを思うと夜も眠れないの。"
            },
            "voice": "card/Card_10/Card_3100004_2/card_3100004_2_022.mp3"
        },
        {
            "index": 23,
            "heroineId": [
                12
            ],
            "name": {
                "default": "日名倉莉子"
            },
            "message": {
                "default": "ああ……。"
            },
            "voice": "card/Card_10/Card_3100004_2/card_3100004_2_023.mp3"
        },
        {
            "index": 24,
            "heroineId": [
                11
            ],
            "name": {
                "default": "宮路まほろ"
            },
            "message": {
                "default": "ちなみにどんな犬なの？"
            },
            "voice": "card/Card_10/Card_3100004_2/card_3100004_2_024.mp3"
        },
        {
            "index": 25,
            "heroineId": [
                10
            ],
            "name": {
                "default": "神室絢"
            },
            "message": {
                "default": "ちょっと大きめのポメラニアン。\nすごくかわいいの。"
            },
            "voice": "card/Card_10/Card_3100004_2/card_3100004_2_025.mp3"
        },
        {
            "index": 26,
            "heroineId": [
                9
            ],
            "name": {
                "default": "夜峰美晴"
            },
            "message": {
                "default": "それを、買いたいの？"
            },
            "voice": "card/Card_10/Card_3100004_2/card_3100004_2_026.mp3"
        },
        {
            "index": 27,
            "heroineId": [
                10
            ],
            "name": {
                "default": "神室絢"
            },
            "message": {
                "default": "ううん、救いたいの。"
            },
            "voice": "card/Card_10/Card_3100004_2/card_3100004_2_027.mp3"
        },
        {
            "index": 28,
            "heroineId": [
                9
            ],
            "name": {
                "default": "夜峰美晴"
            },
            "message": {
                "default": "えっ？"
            },
            "voice": "card/Card_10/Card_3100004_2/card_3100004_2_028.mp3"
        },
        {
            "index": 29,
            "heroineId": [
                10
            ],
            "name": {
                "default": "神室絢"
            },
            "message": {
                "default": "もう、大きくなってきちゃって、定価の半額になってるの。\nこのままだったら……、処分されちゃうかも。"
            },
            "voice": "card/Card_10/Card_3100004_2/card_3100004_2_029.mp3"
        },
        {
            "index": 30,
            "heroineId": [
                12
            ],
            "name": {
                "default": "日名倉莉子"
            },
            "message": {
                "default": "ほんとに？"
            },
            "voice": "card/Card_10/Card_3100004_2/card_3100004_2_030.mp3"
        },
        {
            "index": 31,
            "heroineId": [
                10
            ],
            "name": {
                "default": "神室絢"
            },
            "message": {
                "default": "私、しばらくペットショップの店員になる。"
            },
            "voice": "card/Card_10/Card_3100004_2/card_3100004_2_031.mp3"
        },
        {
            "index": 32,
            "heroineId": [
                9
            ],
            "name": {
                "default": "夜峰美晴"
            },
            "message": {
                "default": "そのお店、スタッフ募集してるの？"
            },
            "voice": "card/Card_10/Card_3100004_2/card_3100004_2_032.mp3"
        },
        {
            "index": 33,
            "heroineId": [
                10
            ],
            "name": {
                "default": "神室絢"
            },
            "message": {
                "default": "ううん、してない。\nでも、頼めばなんとかなるかも。"
            },
            "voice": "card/Card_10/Card_3100004_2/card_3100004_2_033.mp3"
        },
        {
            "index": 34,
            "heroineId": [
                12
            ],
            "name": {
                "default": "日名倉莉子"
            },
            "message": {
                "default": "ちょっと落ち着いたら？"
            },
            "voice": "card/Card_10/Card_3100004_2/card_3100004_2_034.mp3"
        },
        {
            "index": 35,
            "heroineId": [
                10
            ],
            "name": {
                "default": "神室絢"
            },
            "message": {
                "default": "落ち着いてなんていられないの。\nもう決めたの。"
            },
            "voice": "card/Card_10/Card_3100004_2/card_3100004_2_035.mp3"
        },
        {
            "index": 36,
            "heroineId": [
                9
            ],
            "name": {
                "default": "夜峰美晴"
            },
            "message": {
                "default": "うーん、困ったね……。"
            },
            "voice": "card/Card_10/Card_3100004_2/card_3100004_2_036.mp3"
        },
        {
            "index": 37,
            "heroineId": [
                12
            ],
            "name": {
                "default": "日名倉莉子"
            },
            "message": {
                "default": "まあ、ちょっと話そっか。"
            },
            "voice": "card/Card_10/Card_3100004_2/card_3100004_2_037.mp3"
        },
        {
            "index": 38,
            "heroineId": [
                10
            ],
            "name": {
                "default": "神室絢"
            },
            "message": {
                "default": "ごめん、余計なこと聞いて。\nありがとう。"
            },
            "voice": "card/Card_10/Card_3100004_2/card_3100004_2_038.mp3"
        },
        {
            "index": 39,
            "heroineId": [
                9
            ],
            "name": {
                "default": "夜峰美晴"
            },
            "message": {
                "default": "絢、ちょっと待って、絢！"
            },
            "voice": "card/Card_10/Card_3100004_2/card_3100004_2_039.mp3"
        },
        {
            "index": 40,
            "heroineId": [
                10
            ],
            "name": {
                "default": "神室絢"
            },
            "message": {
                "default": "（これでいいんだ。\n出来るだけのことをやる。）"
            },
            "voice": "card/Card_10/Card_3100004_2/card_3100004_2_040.mp3"
        },
        {
            "index": 41,
            "heroineId": [
                10
            ],
            "name": {
                "default": "神室絢"
            },
            "message": {
                "default": "（そうだよ、私小さい頃から動物好きだったじゃん。）"
            },
            "voice": "card/Card_10/Card_3100004_2/card_3100004_2_041.mp3"
        },
        {
            "index": 42,
            "heroineId": [
                10
            ],
            "name": {
                "default": "神室絢"
            },
            "message": {
                "default": "（ペットショップの店員は天職だ。\nうん、きっとそうだ。）"
            },
            "voice": "card/Card_10/Card_3100004_2/card_3100004_2_042.mp3"
        },
        {
            "index": 43,
            "heroineId": [
                10
            ],
            "name": {
                "default": "神室絢"
            },
            "message": {
                "default": "（あの子のそばに、少しでも長くいられたらそれでいい。）"
            },
            "voice": "card/Card_10/Card_3100004_2/card_3100004_2_043.mp3"
        },
        {
            "index": 44,
            "heroineId": [
                10
            ],
            "name": {
                "default": "神室絢"
            },
            "message": {
                "default": "……あれ？\nえっ？　いない……。"
            },
            "voice": "card/Card_10/Card_3100004_2/card_3100004_2_044.mp3"
        },
        {
            "index": 45,
            "heroineId": [
                0
            ],
            "name": {
                "default": "ペットショップ店員"
            },
            "message": {
                "default": "あ、いらっしゃいませ。あの子、昨日いいご縁がありまして。\nすぐに引き取られたんですよ。"
            },
            "voice": ""
        },
        {
            "index": 46,
            "heroineId": [
                10
            ],
            "name": {
                "default": "神室絢"
            },
            "message": {
                "default": "……。"
            },
            "voice": "card/Card_10/Card_3100004_2/card_3100004_2_046.mp3"
        },
        {
            "index": 47,
            "heroineId": [
                0
            ],
            "name": {
                "default": "ペットショップ店員"
            },
            "message": {
                "default": "また、かわいい子が入る予定ですので、\nしばらくお待ちくださいね。"
            },
            "voice": ""
        },
        {
            "index": 48,
            "heroineId": [
                10
            ],
            "name": {
                "default": "神室絢"
            },
            "message": {
                "default": "……。"
            },
            "voice": "card/Card_10/Card_3100004_2/card_3100004_2_048.mp3"
        },
        {
            "index": 49,
            "heroineId": [
                0
            ],
            "name": {
                "default": "ペットショップ店員"
            },
            "message": {
                "default": "……お客さん？"
            },
            "voice": ""
        },
        {
            "index": 50,
            "heroineId": [
                10
            ],
            "name": {
                "default": "神室絢"
            },
            "message": {
                "default": "（いいご縁……。）"
            },
            "voice": "card/Card_10/Card_3100004_2/card_3100004_2_050.mp3"
        },
        {
            "index": 51,
            "heroineId": [
                10
            ],
            "name": {
                "default": "神室絢"
            },
            "message": {
                "default": "……よかったじゃん。"
            },
            "voice": "card/Card_10/Card_3100004_2/card_3100004_2_051.mp3"
        },
        {
            "index": 52,
            "heroineId": [
                10
            ],
            "name": {
                "default": "神室絢"
            },
            "message": {
                "default": "私、あなたのこと本当に……、好きだった。"
            },
            "voice": "card/Card_10/Card_3100004_2/card_3100004_2_052.mp3"
        },
        {
            "index": 53,
            "heroineId": [
                10
            ],
            "name": {
                "default": "神室絢"
            },
            "message": {
                "default": "さようなら……。\n元気でね。"
            },
            "voice": "card/Card_10/Card_3100004_2/card_3100004_2_053.mp3"
        },
        {
            "index": 54,
            "heroineId": [
                0
            ],
            "name": {
                "default": "ポメラニアン"
            },
            "message": {
                "default": "ワンワンクゥーン"
            },
            "voice": ""
        },
        {
            "index": 55,
            "heroineId": [
                10
            ],
            "name": {
                "default": "神室絢"
            },
            "message": {
                "default": "えっ？\n……ええー？"
            },
            "voice": "card/Card_10/Card_3100004_2/card_3100004_2_054.mp3"
        },
        {
            "index": 56,
            "heroineId": [
                10
            ],
            "name": {
                "default": "神室絢"
            },
            "message": {
                "default": "キミ……。\nなんでここにいるの？"
            },
            "voice": "card/Card_10/Card_3100004_2/card_3100004_2_055.mp3"
        },
        {
            "index": 57,
            "heroineId": [
                0
            ],
            "name": {
                "default": "お婆さん"
            },
            "message": {
                "default": "これ、ご迷惑ですよ、やめなさい。"
            },
            "voice": ""
        },
        {
            "index": 58,
            "heroineId": [
                10
            ],
            "name": {
                "default": "神室絢"
            },
            "message": {
                "default": "この子の、飼い主さんですか？"
            },
            "voice": "card/Card_10/Card_3100004_2/card_3100004_2_057.mp3"
        },
        {
            "index": 59,
            "heroineId": [
                0
            ],
            "name": {
                "default": "お婆さん"
            },
            "message": {
                "default": "ええ、そうなんですけどね、\n昨日買ったばっかりで、まだなついてなくて。"
            },
            "voice": ""
        },
        {
            "index": 60,
            "heroineId": [
                10
            ],
            "name": {
                "default": "神室絢"
            },
            "message": {
                "default": "……可愛いですね。"
            },
            "voice": "card/Card_10/Card_3100004_2/card_3100004_2_059.mp3"
        },
        {
            "index": 61,
            "heroineId": [
                0
            ],
            "name": {
                "default": "お婆さん"
            },
            "message": {
                "default": "ええ、ひとめぼれしちゃってね。\n私、1人暮らしなものだから、つい買っちゃったの。"
            },
            "voice": ""
        },
        {
            "index": 62,
            "heroineId": [
                10
            ],
            "name": {
                "default": "神室絢"
            },
            "message": {
                "default": "そうなんですか。"
            },
            "voice": "card/Card_10/Card_3100004_2/card_3100004_2_061.mp3"
        },
        {
            "index": 63,
            "heroineId": [
                0
            ],
            "name": {
                "default": "お婆さん"
            },
            "message": {
                "default": "なんだかこの子……。\nあなたに随分なついてるみたい。"
            },
            "voice": ""
        },
        {
            "index": 64,
            "heroineId": [
                10
            ],
            "name": {
                "default": "神室絢"
            },
            "message": {
                "default": "（言わない方がいいよね。\nペットショップに通ってたことなんて。）"
            },
            "voice": "card/Card_10/Card_3100004_2/card_3100004_2_063.mp3"
        },
        {
            "index": 65,
            "heroineId": [
                0
            ],
            "name": {
                "default": "お婆さん"
            },
            "message": {
                "default": "これ、いいかげんにおし、あや。"
            },
            "voice": ""
        },
        {
            "index": 66,
            "heroineId": [
                10
            ],
            "name": {
                "default": "神室絢"
            },
            "message": {
                "default": "……え？"
            },
            "voice": "card/Card_10/Card_3100004_2/card_3100004_2_065.mp3"
        },
        {
            "index": 67,
            "heroineId": [
                0
            ],
            "name": {
                "default": "お婆さん"
            },
            "message": {
                "default": "そんなにすり寄ったら、\nお姉さんの服が汚れちゃうでしょ。"
            },
            "voice": ""
        },
        {
            "index": 68,
            "heroineId": [
                10
            ],
            "name": {
                "default": "神室絢"
            },
            "message": {
                "default": "今、なんて？"
            },
            "voice": "card/Card_10/Card_3100004_2/card_3100004_2_067.mp3"
        },
        {
            "index": 69,
            "heroineId": [
                0
            ],
            "name": {
                "default": "お婆さん"
            },
            "message": {
                "default": "はい？"
            },
            "voice": ""
        },
        {
            "index": 70,
            "heroineId": [
                10
            ],
            "name": {
                "default": "神室絢"
            },
            "message": {
                "default": "今、この子の事、なんて呼びました？"
            },
            "voice": "card/Card_10/Card_3100004_2/card_3100004_2_069.mp3"
        },
        {
            "index": 71,
            "heroineId": [
                0
            ],
            "name": {
                "default": "お婆さん"
            },
            "message": {
                "default": "あや……、ですけど？"
            },
            "voice": ""
        },
        {
            "index": 72,
            "heroineId": [
                10
            ],
            "name": {
                "default": "神室絢"
            },
            "message": {
                "default": "私も……。\nあやって名前なんです。"
            },
            "voice": "card/Card_10/Card_3100004_2/card_3100004_2_071.mp3"
        },
        {
            "index": 73,
            "heroineId": [
                0
            ],
            "name": {
                "default": "お婆さん"
            },
            "message": {
                "default": "あらやだ、偶然。\n面白いわね。"
            },
            "voice": ""
        },
        {
            "index": 74,
            "heroineId": [
                10
            ],
            "name": {
                "default": "神室絢"
            },
            "message": {
                "default": "（偶然じゃない、きっとこれは“運命”なんだ。）"
            },
            "voice": "card/Card_10/Card_3100004_2/card_3100004_2_073.mp3"
        },
        {
            "index": 75,
            "heroineId": [
                0
            ],
            "name": {
                "default": "お婆さん"
            },
            "message": {
                "default": "あら、もうこんな時間？　そろそろ行かなきゃ……。\nそれじゃ、ごめんください。"
            },
            "voice": ""
        },
        {
            "index": 76,
            "heroineId": [
                10
            ],
            "name": {
                "default": "神室絢"
            },
            "message": {
                "default": "あの、時々、会ってもいいですか？　この子、可愛いし。\nえっと……、名前も一緒だし。"
            },
            "voice": "card/Card_10/Card_3100004_2/card_3100004_2_075.mp3"
        },
        {
            "index": 77,
            "heroineId": [
                0
            ],
            "name": {
                "default": "お婆さん"
            },
            "message": {
                "default": "もちろん。毎日この公園で散歩してますから。\nぜひ会いに来てちょうだい。"
            },
            "voice": ""
        },
        {
            "index": 78,
            "heroineId": [
                10
            ],
            "name": {
                "default": "神室絢"
            },
            "message": {
                "default": "ありがとうございます。"
            },
            "voice": "card/Card_10/Card_3100004_2/card_3100004_2_077.mp3"
        },
        {
            "index": 79,
            "heroineId": [
                10
            ],
            "name": {
                "default": "神室絢"
            },
            "message": {
                "default": "（いい人にもらわれたね。）"
            },
            "voice": "card/Card_10/Card_3100004_2/card_3100004_2_078.mp3"
        },
        {
            "index": 80,
            "heroineId": [
                10
            ],
            "name": {
                "default": "神室絢"
            },
            "message": {
                "default": "またね、あや！"
            },
            "voice": "card/Card_10/Card_3100004_2/card_3100004_2_079.mp3"
        }
    ]
}