{
    "Txt_Name": "Card_3030004_2",
    "Dialogue": [
        {
            "index": 1,
            "heroineId": [
                3
            ],
            "name": {
                "default": "鹿野志穂"
            },
            "message": {
                "default": "モフクー？\nモフクー？"
            },
            "voice": "card/Card_03/Card_3030004_2/card_3030004_2_001.mp3"
        },
        {
            "index": 2,
            "heroineId": [
                0
            ],
            "name": {
                "default": "マネージャー"
            },
            "message": {
                "default": "やっぱり、どこにもいないね……。"
            },
            "voice": ""
        },
        {
            "index": 3,
            "heroineId": [
                3
            ],
            "name": {
                "default": "鹿野志穂"
            },
            "message": {
                "default": "おーい。大好きな猫缶買ってきたぞー。\nいつもなら、呼ぶとすぐに出てくるのに……。"
            },
            "voice": "card/Card_03/Card_3030004_2/card_3030004_2_003.mp3"
        },
        {
            "index": 4,
            "heroineId": [
                0
            ],
            "name": {
                "default": "マネージャー"
            },
            "message": {
                "default": "あっ、それ使おう！"
            },
            "voice": ""
        },
        {
            "index": 5,
            "heroineId": [
                3
            ],
            "name": {
                "default": "鹿野志穂"
            },
            "message": {
                "default": "この猫缶？"
            },
            "voice": "card/Card_03/Card_3030004_2/card_3030004_2_005.mp3"
        },
        {
            "index": 6,
            "heroineId": [
                0
            ],
            "name": {
                "default": "マネージャー"
            },
            "message": {
                "default": "こうやって、点々と置いて、おびき出すの……。"
            },
            "voice": ""
        },
        {
            "index": 7,
            "heroineId": [
                3
            ],
            "name": {
                "default": "鹿野志穂"
            },
            "message": {
                "default": "ジャーマネにしてはいい作戦かも。"
            },
            "voice": "card/Card_03/Card_3030004_2/card_3030004_2_007.mp3"
        },
        {
            "index": 8,
            "heroineId": [
                0
            ],
            "name": {
                "default": "マネージャー"
            },
            "message": {
                "default": "「ジャーマネにしては」は余計。"
            },
            "voice": ""
        },
        {
            "index": 9,
            "heroineId": [
                3
            ],
            "name": {
                "default": "鹿野志穂"
            },
            "message": {
                "default": "よし……。\n猫缶を少しずつ出して、点々と置いて……。"
            },
            "voice": "card/Card_03/Card_3030004_2/card_3030004_2_009.mp3"
        },
        {
            "index": 10,
            "heroineId": [
                0
            ],
            "name": {
                "default": "マネージャー"
            },
            "message": {
                "default": "あっ！\nあれ見て！"
            },
            "voice": ""
        },
        {
            "index": 11,
            "heroineId": [
                3
            ],
            "name": {
                "default": "鹿野志穂"
            },
            "message": {
                "default": "モフクが来た！？"
            },
            "voice": "card/Card_03/Card_3030004_2/card_3030004_2_011.mp3"
        },
        {
            "index": 12,
            "heroineId": [
                0
            ],
            "name": {
                "default": "マネージャー"
            },
            "message": {
                "default": "違う、あれ！"
            },
            "voice": ""
        },
        {
            "index": 13,
            "heroineId": [
                3
            ],
            "name": {
                "default": "鹿野志穂"
            },
            "message": {
                "default": "あっ！\nハトが猫缶を食べてる！"
            },
            "voice": "card/Card_03/Card_3030004_2/card_3030004_2_013.mp3"
        },
        {
            "index": 14,
            "heroineId": [
                0
            ],
            "name": {
                "default": "マネージャー"
            },
            "message": {
                "default": "すごい数のハトが集まってきてる！"
            },
            "voice": ""
        },
        {
            "index": 15,
            "heroineId": [
                3
            ],
            "name": {
                "default": "鹿野志穂"
            },
            "message": {
                "default": "シッ、シッ、向こう行け！"
            },
            "voice": "card/Card_03/Card_3030004_2/card_3030004_2_015.mp3"
        },
        {
            "index": 16,
            "heroineId": [
                0
            ],
            "name": {
                "default": "マネージャー"
            },
            "message": {
                "default": "あー！"
            },
            "voice": ""
        },
        {
            "index": 17,
            "heroineId": [
                3
            ],
            "name": {
                "default": "鹿野志穂"
            },
            "message": {
                "default": "カラスもやってきた！"
            },
            "voice": "card/Card_03/Card_3030004_2/card_3030004_2_017.mp3"
        },
        {
            "index": 18,
            "heroineId": [
                0
            ],
            "name": {
                "default": "マネージャー"
            },
            "message": {
                "default": "修羅場のようになってる……。"
            },
            "voice": ""
        },
        {
            "index": 19,
            "heroineId": [
                3
            ],
            "name": {
                "default": "鹿野志穂"
            },
            "message": {
                "default": "猫缶、全部食べられた……。"
            },
            "voice": "card/Card_03/Card_3030004_2/card_3030004_2_019.mp3"
        },
        {
            "index": 20,
            "heroineId": [
                0
            ],
            "name": {
                "default": "マネージャー"
            },
            "message": {
                "default": "なんか……。\nごめん……。"
            },
            "voice": ""
        },
        {
            "index": 21,
            "heroineId": [
                3
            ],
            "name": {
                "default": "鹿野志穂"
            },
            "message": {
                "default": "せっかくモフクを喜ばせようと並んで買ったのに……。"
            },
            "voice": "card/Card_03/Card_3030004_2/card_3030004_2_021.mp3"
        },
        {
            "index": 22,
            "heroineId": [
                0
            ],
            "name": {
                "default": "マネージャー"
            },
            "message": {
                "default": "並んで買ったんだ……。"
            },
            "voice": ""
        },
        {
            "index": 23,
            "heroineId": [
                0
            ],
            "name": {
                "default": "子猫"
            },
            "message": {
                "default": "ニャー"
            },
            "voice": ""
        },
        {
            "index": 24,
            "heroineId": [
                3
            ],
            "name": {
                "default": "鹿野志穂"
            },
            "message": {
                "default": "モフク……。"
            },
            "voice": "card/Card_03/Card_3030004_2/card_3030004_2_023.mp3"
        },
        {
            "index": 25,
            "heroineId": [
                0
            ],
            "name": {
                "default": "マネージャー"
            },
            "message": {
                "default": "ん……？"
            },
            "voice": ""
        },
        {
            "index": 26,
            "heroineId": [
                3
            ],
            "name": {
                "default": "鹿野志穂"
            },
            "message": {
                "default": "この鳴き声は……、モフク！"
            },
            "voice": "card/Card_03/Card_3030004_2/card_3030004_2_025.mp3"
        },
        {
            "index": 27,
            "heroineId": [
                0
            ],
            "name": {
                "default": "マネージャー"
            },
            "message": {
                "default": "どこ？\nどこにいる？"
            },
            "voice": ""
        },
        {
            "index": 28,
            "heroineId": [
                3
            ],
            "name": {
                "default": "鹿野志穂"
            },
            "message": {
                "default": "あ、あそこ……。"
            },
            "voice": "card/Card_03/Card_3030004_2/card_3030004_2_027.mp3"
        },
        {
            "index": 29,
            "heroineId": [
                0
            ],
            "name": {
                "default": "マネージャー"
            },
            "message": {
                "default": "えっ……？"
            },
            "voice": ""
        },
        {
            "index": 30,
            "heroineId": [
                3
            ],
            "name": {
                "default": "鹿野志穂"
            },
            "message": {
                "default": "小さい女の子が抱っこしてる……。"
            },
            "voice": "card/Card_03/Card_3030004_2/card_3030004_2_029.mp3"
        },
        {
            "index": 31,
            "heroineId": [
                0
            ],
            "name": {
                "default": "マネージャー"
            },
            "message": {
                "default": "あれが、モフク……？"
            },
            "voice": ""
        },
        {
            "index": 32,
            "heroineId": [
                3
            ],
            "name": {
                "default": "鹿野志穂"
            },
            "message": {
                "default": "うん……。"
            },
            "voice": "card/Card_03/Card_3030004_2/card_3030004_2_031.mp3"
        },
        {
            "index": 33,
            "heroineId": [
                0
            ],
            "name": {
                "default": "マネージャー"
            },
            "message": {
                "default": "近くにいるの、お母さんだね……。"
            },
            "voice": ""
        },
        {
            "index": 34,
            "heroineId": [
                3
            ],
            "name": {
                "default": "鹿野志穂"
            },
            "message": {
                "default": "何か言ってる……。\nお願いしてるみたい……。"
            },
            "voice": "card/Card_03/Card_3030004_2/card_3030004_2_033.mp3"
        },
        {
            "index": 35,
            "heroineId": [
                0
            ],
            "name": {
                "default": "マネージャー"
            },
            "message": {
                "default": "あ、お母さんが頷いた……。"
            },
            "voice": ""
        },
        {
            "index": 36,
            "heroineId": [
                3
            ],
            "name": {
                "default": "鹿野志穂"
            },
            "message": {
                "default": "女の子が大喜びしてる……。"
            },
            "voice": "card/Card_03/Card_3030004_2/card_3030004_2_035.mp3"
        },
        {
            "index": 37,
            "heroineId": [
                0
            ],
            "name": {
                "default": "マネージャー"
            },
            "message": {
                "default": "きっと、モフクはあの女の子に飼われるんだね……。"
            },
            "voice": ""
        },
        {
            "index": 38,
            "heroineId": [
                3
            ],
            "name": {
                "default": "鹿野志穂"
            },
            "message": {
                "default": "優しそうな女の子……。"
            },
            "voice": "card/Card_03/Card_3030004_2/card_3030004_2_037.mp3"
        },
        {
            "index": 39,
            "heroineId": [
                0
            ],
            "name": {
                "default": "マネージャー"
            },
            "message": {
                "default": "よかったじゃない……。"
            },
            "voice": ""
        },
        {
            "index": 40,
            "heroineId": [
                3
            ],
            "name": {
                "default": "鹿野志穂"
            },
            "message": {
                "default": "ちょっと行ってくる。"
            },
            "voice": "card/Card_03/Card_3030004_2/card_3030004_2_039.mp3"
        },
        {
            "index": 41,
            "heroineId": [
                0
            ],
            "name": {
                "default": "マネージャー"
            },
            "message": {
                "default": "何しに行くの？"
            },
            "voice": ""
        },
        {
            "index": 42,
            "heroineId": [
                3
            ],
            "name": {
                "default": "鹿野志穂"
            },
            "message": {
                "default": "モフクをよろしくお願いしますって。"
            },
            "voice": "card/Card_03/Card_3030004_2/card_3030004_2_041.mp3"
        },
        {
            "index": 43,
            "heroineId": [
                0
            ],
            "name": {
                "default": "マネージャー"
            },
            "message": {
                "default": "止めた方がいいんじゃない……？"
            },
            "voice": ""
        },
        {
            "index": 44,
            "heroineId": [
                3
            ],
            "name": {
                "default": "鹿野志穂"
            },
            "message": {
                "default": "じゃ、せめて名前がモフクだってことを伝えないと。"
            },
            "voice": "card/Card_03/Card_3030004_2/card_3030004_2_043.mp3"
        },
        {
            "index": 45,
            "heroineId": [
                0
            ],
            "name": {
                "default": "マネージャー"
            },
            "message": {
                "default": "やめなよ。\nあの猫はもう、モフクじゃない。"
            },
            "voice": ""
        },
        {
            "index": 46,
            "heroineId": [
                3
            ],
            "name": {
                "default": "鹿野志穂"
            },
            "message": {
                "default": "……。"
            },
            "voice": "card/Card_03/Card_3030004_2/card_3030004_2_045.mp3"
        },
        {
            "index": 47,
            "heroineId": [
                0
            ],
            "name": {
                "default": "マネージャー"
            },
            "message": {
                "default": "あの女の子の猫だよ。\nあの女の子がきっと素敵な名前をつけるよ。"
            },
            "voice": ""
        },
        {
            "index": 48,
            "heroineId": [
                3
            ],
            "name": {
                "default": "鹿野志穂"
            },
            "message": {
                "default": "それもそうだな。\nモフク……、幸せになれよ……。"
            },
            "voice": "card/Card_03/Card_3030004_2/card_3030004_2_047.mp3"
        },
        {
            "index": 49,
            "heroineId": [
                0
            ],
            "name": {
                "default": "マネージャー"
            },
            "message": {
                "default": "……はい、これ。"
            },
            "voice": ""
        },
        {
            "index": 50,
            "heroineId": [
                3
            ],
            "name": {
                "default": "鹿野志穂"
            },
            "message": {
                "default": "これは……？"
            },
            "voice": "card/Card_03/Card_3030004_2/card_3030004_2_049.mp3"
        },
        {
            "index": 51,
            "heroineId": [
                0
            ],
            "name": {
                "default": "マネージャー"
            },
            "message": {
                "default": "さっきお茶を買ってきたから。\n一緒に飲もう。"
            },
            "voice": ""
        },
        {
            "index": 52,
            "heroineId": [
                3
            ],
            "name": {
                "default": "鹿野志穂"
            },
            "message": {
                "default": "ジャーマネ……。"
            },
            "voice": "card/Card_03/Card_3030004_2/card_3030004_2_051.mp3"
        },
        {
            "index": 53,
            "heroineId": [
                0
            ],
            "name": {
                "default": "マネージャー"
            },
            "message": {
                "default": "さ、そこに座って。"
            },
            "voice": ""
        },
        {
            "index": 54,
            "heroineId": [
                3
            ],
            "name": {
                "default": "鹿野志穂"
            },
            "message": {
                "default": "それじゃ、遠慮なく。"
            },
            "voice": "card/Card_03/Card_3030004_2/card_3030004_2_053.mp3"
        },
        {
            "index": 55,
            "heroineId": [
                0
            ],
            "name": {
                "default": "マネージャー"
            },
            "message": {
                "default": "はい、どうぞ。"
            },
            "voice": ""
        },
        {
            "index": 56,
            "heroineId": [
                3
            ],
            "name": {
                "default": "鹿野志穂"
            },
            "message": {
                "default": "あんた、いいジャーマネだな。"
            },
            "voice": "card/Card_03/Card_3030004_2/card_3030004_2_055.mp3"
        },
        {
            "index": 57,
            "heroineId": [
                0
            ],
            "name": {
                "default": "マネージャー"
            },
            "message": {
                "default": "あ、ありがとう……。"
            },
            "voice": ""
        },
        {
            "index": 58,
            "heroineId": [
                3
            ],
            "name": {
                "default": "鹿野志穂"
            },
            "message": {
                "default": "どうした？"
            },
            "voice": "card/Card_03/Card_3030004_2/card_3030004_2_057.mp3"
        },
        {
            "index": 59,
            "heroineId": [
                0
            ],
            "name": {
                "default": "マネージャー"
            },
            "message": {
                "default": "いや、志穂に褒められるのは、なんかムズ痒い。"
            },
            "voice": ""
        },
        {
            "index": 60,
            "heroineId": [
                3
            ],
            "name": {
                "default": "鹿野志穂"
            },
            "message": {
                "default": "じゃ、けなしてやろう。"
            },
            "voice": "card/Card_03/Card_3030004_2/card_3030004_2_059.mp3"
        },
        {
            "index": 61,
            "heroineId": [
                0
            ],
            "name": {
                "default": "マネージャー"
            },
            "message": {
                "default": "いや、それは……。"
            },
            "voice": ""
        },
        {
            "index": 62,
            "heroineId": [
                3
            ],
            "name": {
                "default": "鹿野志穂"
            },
            "message": {
                "default": "猫缶の作戦、あれは大失敗だ。"
            },
            "voice": "card/Card_03/Card_3030004_2/card_3030004_2_061.mp3"
        },
        {
            "index": 63,
            "heroineId": [
                0
            ],
            "name": {
                "default": "マネージャー"
            },
            "message": {
                "default": "だから謝ったじゃない……。"
            },
            "voice": ""
        },
        {
            "index": 64,
            "heroineId": [
                3
            ],
            "name": {
                "default": "鹿野志穂"
            },
            "message": {
                "default": "とりあえず、弁償して。"
            },
            "voice": "card/Card_03/Card_3030004_2/card_3030004_2_063.mp3"
        },
        {
            "index": 65,
            "heroineId": [
                0
            ],
            "name": {
                "default": "マネージャー"
            },
            "message": {
                "default": "分ったよ……、いくら？"
            },
            "voice": ""
        },
        {
            "index": 66,
            "heroineId": [
                3
            ],
            "name": {
                "default": "鹿野志穂"
            },
            "message": {
                "default": "猫缶は300円だけど、並んだ時間も考えると……、千円。"
            },
            "voice": "card/Card_03/Card_3030004_2/card_3030004_2_065.mp3"
        },
        {
            "index": 67,
            "heroineId": [
                0
            ],
            "name": {
                "default": "マネージャー"
            },
            "message": {
                "default": "千円！？\n高いよ！"
            },
            "voice": ""
        },
        {
            "index": 68,
            "heroineId": [
                3
            ],
            "name": {
                "default": "鹿野志穂"
            },
            "message": {
                "default": "でも、このお茶が美味しかったから……、チャラにする。"
            },
            "voice": "card/Card_03/Card_3030004_2/card_3030004_2_067.mp3"
        },
        {
            "index": 69,
            "heroineId": [
                0
            ],
            "name": {
                "default": "マネージャー"
            },
            "message": {
                "default": "えっ？"
            },
            "voice": ""
        },
        {
            "index": 70,
            "heroineId": [
                3
            ],
            "name": {
                "default": "鹿野志穂"
            },
            "message": {
                "default": "このお茶は、千円、いや、それ以上の価値がある。\nそういうこと。"
            },
            "voice": "card/Card_03/Card_3030004_2/card_3030004_2_069.mp3"
        }
    ]
}